wpt_interop-0.2.3.dist-info/METADATA
wpt_interop-0.2.3.dist-info/WHEEL
wpt_interop-0.2.3.dist-info/entry_points.txt
wpt_interop/__init__.py
wpt_interop/_wpt_interop.cp313-win_amd64.pyd
wpt_interop/_wpt_interop.pyi
wpt_interop/interop_score.py
wpt_interop/metadata.py
wpt_interop/regressions.py
wpt_interop/repo.py
wpt_interop/runs.py
wpt_interop/score.py
wpt_interop-0.2.3.dist-info/RECORD
